rrc_statewide_api/__init__.py
rrc_statewide_api/parser.py
rrc_statewide_api/utils.py
rrc_statewide_api-1.0.2.dist-info/METADATA
rrc_statewide_api-1.0.2.dist-info/WHEEL
rrc_statewide_api-1.0.2.dist-info/top_level.txt
rrc_statewide_api-1.0.2.dist-info/RECORD
