Metadata-Version: 2.4
Name: rrc-statewide-api
Version: 1.0.2
Summary: A Python parser for Texas RRC Statewide API Data (DBF format)
Author-email: Marcus Salinas <marcus.salinas@example.com>
Classifier: Programming Language :: Python :: 3
Classifier: License :: OSI Approved :: MIT License
Classifier: Operating System :: OS Independent
Requires-Python: >=3.9
Requires-Dist: dbfread>=2.0.7
Provides-Extra: dev
Requires-Dist: pytest; extra == "dev"
Requires-Dist: black; extra == "dev"
Requires-Dist: flake8; extra == "dev"
Requires-Dist: mypy; extra == "dev"
